[
  {
    "external_id": "b62a7174-f72a-4da1-95df-42c5af4fc218",
    "classification": {
      "quality_attributes": [
        "앱 안정성",
        "응답 속도 체감"
      ],
      "sentiment": "매우 부정",
      "sentiment_score": -20,
      "severity": "이탈/강한 부정",
      "severity_multiplier": 2,
      "score_reality": 40
    }
  },
  {
    "external_id": "e5fe331b-0d04-44c2-95d6-17ab60415386",
    "classification": {
      "quality_attributes": [
        "시각적 피로도"
      ],
      "sentiment": "부정",
      "sentiment_score": -10,
      "severity": "일반",
      "severity_multiplier": 1,
      "score_reality": 70
    }
  },
  {
    "external_id": "2d410283-4bfb-4c1e-9e25-951fb5b71af5",
    "classification": {
      "quality_attributes": [
        "처리 정확성"
      ],
      "sentiment": "매우 부정",
      "sentiment_score": -20,
      "severity": "반복/누적",
      "severity_multiplier": 1.5,
      "score_reality": 50
    }
  },
  {
    "external_id": "0eb727c4-c1fb-4869-9aae-31e629fa00ab",
    "classification": {
      "quality_attributes": [
        "가격 대비 가치"
      ],
      "sentiment": "긍정",
      "sentiment_score": 10,
      "severity": "일반",
      "severity_multiplier": 1,
      "score_reality": 90
    }
  },
  {
    "external_id": "dc38a946-b778-4151-92f4-317e76305159",
    "classification": {
      "quality_attributes": [
        "앱 안정성"
      ],
      "sentiment": "매우 부정",
      "sentiment_score": -20,
      "severity": "이탈/강한 부정",
      "severity_multiplier": 2,
      "score_reality": 40
    }
  },
  {
    "external_id": "ef2c1a01-a53f-4fbd-9e41-27c1a3fe72fa",
    "classification": {
      "quality_attributes": [
        "UI 일관성",
        "정보구조 적합성"
      ],
      "sentiment": "부정",
      "sentiment_score": -10,
      "severity": "일반",
      "severity_multiplier": 1,
      "score_reality": 70
    }
  },
  {
    "external_id": "9a786728-4fc3-4f9d-a412-a788a140f88d",
    "classification": {
      "quality_attributes": [
        "응답 속도 체감"
      ],
      "sentiment": "매우 부정",
      "sentiment_score": -20,
      "severity": "이탈/강한 부정",
      "severity_multiplier": 2,
      "score_reality": 40
    }
  },
  {
    "external_id": "6e424664-bf77-4b50-b7cd-b532b69a048f",
    "classification": {
      "quality_attributes": [
        "UI 일관성"
      ],
      "sentiment": "중립",
      "sentiment_score": 0,
      "severity": "일반",
      "severity_multiplier": 1,
      "score_reality": 80
    }
  },
  {
    "external_id": "c7c0821a-b88d-4a59-a65c-c7c5b834223b",
    "classification": null
  },
  {
    "external_id": "76740844-df7d-48a4-b9c4-bc8305eba31d",
    "classification": {
      "quality_attributes": [
        "프로모션 체감",
        "정책 투명성"
      ],
      "sentiment": "매우 부정",
      "sentiment_score": -20,
      "severity": "이탈/강한 부정",
      "severity_multiplier": 2,
      "score_reality": 40
    }
  },
  {
    "external_id": "74a97b6e-0cee-4497-8ae4-b5e33c712cb4",
    "classification": {
      "quality_attributes": [
        "처리 정확성",
        "보안·개인정보"
      ],
      "sentiment": "매우 부정",
      "sentiment_score": -20,
      "severity": "반복/누적",
      "severity_multiplier": 1.5,
      "score_reality": 50
    }
  },
  {
    "external_id": "57686294-cfbb-4bba-b9b9-e50a3d4fe9b5",
    "classification": {
      "quality_attributes": [
        "로그인·인증"
      ],
      "sentiment": "매우 부정",
      "sentiment_score": -20,
      "severity": "반복/누적",
      "severity_multiplier": 1.5,
      "score_reality": 50
    }
  },
  {
    "external_id": "8f1702ff-5329-435f-aa6a-624619652590",
    "classification": {
      "quality_attributes": [
        "UI 일관성",
        "정보구조 적합성"
      ],
      "sentiment": "매우 부정",
      "sentiment_score": -20,
      "severity": "반복/누적",
      "severity_multiplier": 1.5,
      "score_reality": 50
    }
  },
  {
    "external_id": "14ba5274-ecd9-4e02-a7f0-43102ec5f29c",
    "classification": {
      "quality_attributes": [
        "앱 안정성",
        "호환성"
      ],
      "sentiment": "매우 부정",
      "sentiment_score": -20,
      "severity": "반복+이탈",
      "severity_multiplier": 2.5,
      "score_reality": 30
    }
  },
  {
    "external_id": "56175ec1-10b0-4483-ade5-1697c7946306",
    "classification": {
      "quality_attributes": [
        "로딩 속도",
        "로그인·인증",
        "앱 안정성"
      ],
      "sentiment": "매우 부정",
      "sentiment_score": -20,
      "severity": "반복/누적",
      "severity_multiplier": 1.5,
      "score_reality": 50
    }
  },
  {
    "external_id": "985181ff-2415-46ed-8c90-5f0bd4c94c54",
    "classification": {
      "quality_attributes": [
        "처리 정확성"
      ],
      "sentiment": "부정",
      "sentiment_score": -10,
      "severity": "일반",
      "severity_multiplier": 1,
      "score_reality": 70
    }
  },
  {
    "external_id": "cf8d9e84-6244-417a-8b22-4f285708bbff",
    "classification": {
      "quality_attributes": [
        "정책 투명성"
      ],
      "sentiment": "매우 부정",
      "sentiment_score": -20,
      "severity": "이탈/강한 부정",
      "severity_multiplier": 2,
      "score_reality": 40
    }
  },
  {
    "external_id": "d1ad3ed6-1faa-4b33-bb56-c5f899d8ace4",
    "classification": {
      "quality_attributes": [
        "호환성",
        "앱 안정성"
      ],
      "sentiment": "부정",
      "sentiment_score": -10,
      "severity": "반복/누적",
      "severity_multiplier": 1.5,
      "score_reality": 65
    }
  },
  {
    "external_id": "0b0fbaae-fd8a-41bb-861d-324bbfa26772",
    "classification": {
      "quality_attributes": [
        "응답 속도 체감"
      ],
      "sentiment": "매우 부정",
      "sentiment_score": -20,
      "severity": "이탈/강한 부정",
      "severity_multiplier": 2,
      "score_reality": 40
    }
  },
  {
    "external_id": "b5b6ebcb-71c3-439b-ab27-63fa6b2ffb3d",
    "classification": {
      "quality_attributes": [
        "프로모션 체감"
      ],
      "sentiment": "부정",
      "sentiment_score": -10,
      "severity": "일반",
      "severity_multiplier": 1,
      "score_reality": 70
    }
  }
]